MANIFEST.in
README.md
setup.py
apidou/__init__.py
apidou/apidou.py
apidou.egg-info/PKG-INFO
apidou.egg-info/SOURCES.txt
apidou.egg-info/dependency_links.txt
apidou.egg-info/requires.txt
apidou.egg-info/top_level.txt