Metadata-Version: 1.1
Name: apidou
Version: 0.2.2
Summary: Module to communicate with APIdou, the connected plush
Home-page: http://github.com/iadjedj/apidou
Author: Ilann Adjedj
Author-email: ilann@apidou.fr
License: Beerware
Platform: UNKNOWN
Classifier: Programming Language :: Python
Classifier: Development Status :: 1 - Planning
Classifier: License :: OSI Approved
Classifier: Natural Language :: French
Classifier: Operating System :: OS Independent
Classifier: Programming Language :: Python :: 2.7
Classifier: Topic :: Communications
